dwdparse/__init__.py
dwdparse/__main__.py
dwdparse/api.py
dwdparse/cli.py
dwdparse/parsers.py
dwdparse/stations.py
dwdparse/units.py
dwdparse/utils.py
dwdparse-0.9.20.dist-info/licenses/LICENSE
dwdparse-0.9.20.dist-info/METADATA
dwdparse-0.9.20.dist-info/WHEEL
dwdparse-0.9.20.dist-info/entry_points.txt
dwdparse-0.9.20.dist-info/top_level.txt
dwdparse-0.9.20.dist-info/RECORD
