Metadata-Version: 2.4
Name: dwdparse
Version: 0.9.20
Summary: Parsers for DWD's open weather data.
Author: Jakob de Maeyer
Author-email: jakob@naboa.de
Project-URL: Source, https://github.com/jdemaeyer/dwdparse/
Project-URL: Tracker, https://github.com/jdemaeyer/dwdparse/issues/
Classifier: Programming Language :: Python :: 3
Classifier: License :: OSI Approved :: MIT License
Classifier: Operating System :: OS Independent
Requires-Python: >=3.8
License-File: LICENSE
Provides-Extra: lean
Requires-Dist: ijson; extra == "lean"
Provides-Extra: radar
Requires-Dist: h5py; extra == "radar"
Provides-Extra: all
Requires-Dist: h5py; extra == "all"
Requires-Dist: ijson; extra == "all"
Dynamic: author
Dynamic: author-email
Dynamic: classifier
Dynamic: description
Dynamic: description-content-type
Dynamic: license-file
Dynamic: project-url
Dynamic: provides-extra
Dynamic: requires-python
Dynamic: summary
